dist/ka_utg-2023.2.3.tar.gz
ka_utg/__init__.py
ka_utg/__version__.py
ka_utg/aoa.py
ka_utg/aod.py
ka_utg/aoo.py
ka_utg/aos.py
ka_utg/args.py
ka_utg/arr.py
ka_utg/arrs.py
ka_utg/cmd.py
ka_utg/cmdline.py
ka_utg/col.py
ka_utg/d2v.py
ka_utg/d3v.py
ka_utg/dic.py
ka_utg/doa.py
ka_utg/dod.py
ka_utg/doo.py
ka_utg/evt.py
ka_utg/exc.py
ka_utg/file.py
ka_utg/fnc.py
ka_utg/log.py
ka_utg/msg.py
ka_utg/obj.py
ka_utg/py.typed
ka_utg/range.py
ka_utg/setdic.py
ka_utg/str.py
ka_utg/timer.py
ka_utg/utg.py
ka_utg/ver.py
ka_utg/data/__init__.py
ka_utg/data/log.main.tenant.yml
ka_utg/data/log.yml
ka_utg-2023.2.3.dist-info/LICENSE.txt
ka_utg-2023.2.3.dist-info/METADATA
ka_utg-2023.2.3.dist-info/WHEEL
ka_utg-2023.2.3.dist-info/entry_points.txt
ka_utg-2023.2.3.dist-info/top_level.txt
ka_utg-2023.2.3.dist-info/RECORD
